sockx/__init__.py
sockx/constants.py
sockx/receiver/__init__.py
sockx/receiver/receiver.py
sockx/receiver/tcp_file_receiver.py
sockx/receiver/tcp_message_receiver.py
sockx/receiver/udp_file_receiver.py
sockx/receiver/udp_message_receiver.py
sockx/sender/__init__.py
sockx/sender/sender.py
sockx/sender/tcp_file_sender.py
sockx/sender/tcp_message_sender.py
sockx/sender/udp_file_sender.py
sockx/sender/udp_message_sender.py
sockx/utils/__init__.py
sockx/utils/error.py
sockx-0.1a8.dist-info/LICENSE
sockx-0.1a8.dist-info/METADATA
sockx-0.1a8.dist-info/WHEEL
sockx-0.1a8.dist-info/top_level.txt
sockx-0.1a8.dist-info/RECORD
